saefarer/__init__.py
saefarer/constants.py
saefarer/protocols.py
saefarer/sae.py
saefarer/utils.py
saefarer/adapters/__init__.py
saefarer/adapters/tokenizers.py
saefarer/analysis/__init__.py
saefarer/analysis/analyze.py
saefarer/analysis/config.py
saefarer/analysis/database.py
saefarer/analysis/feature_analysis.py
saefarer/analysis/inference.py
saefarer/analysis/model_and_dataset.py
saefarer/analysis/types.py
saefarer/static/saefarer.css
saefarer/static/widget.js
saefarer/training/__init__.py
saefarer/training/activations_store.py
saefarer/training/config.py
saefarer/training/logger.py
saefarer/training/train.py
saefarer/widget/__init__.py
saefarer/widget/config.py
saefarer/widget/widget.py
saefarer-0.0.2.dist-info/METADATA
saefarer-0.0.2.dist-info/WHEEL
saefarer-0.0.2.dist-info/licenses/LICENSE
saefarer-0.0.2.dist-info/RECORD
