Metadata-Version: 2.4
Name: saefarer
Version: 0.0.2
License-File: LICENSE
Requires-Python: >=3.8
Requires-Dist: anywidget<0.10,>=0.9.13
Requires-Dist: datasets>=2.21.0
Requires-Dist: einops
Requires-Dist: numba
Requires-Dist: numpy
Requires-Dist: scikit-learn
Requires-Dist: scipy
Requires-Dist: torch
Requires-Dist: transformers
Requires-Dist: umap-learn
Provides-Extra: dev
Requires-Dist: anywidget[dev]>=0.9.13; extra == 'dev'
Requires-Dist: build; extra == 'dev'
Requires-Dist: jupyterlab>=4.3.4; extra == 'dev'
Requires-Dist: pytest; extra == 'dev'
Requires-Dist: ruff>=0.9.3; extra == 'dev'
Requires-Dist: sphinx; extra == 'dev'
Requires-Dist: twine; extra == 'dev'
Provides-Extra: examples
Requires-Dist: openpyxl; extra == 'examples'
Provides-Extra: tensorboard
Requires-Dist: tensorboard; extra == 'tensorboard'
Provides-Extra: wandb
Requires-Dist: wandb; extra == 'wandb'
